genlm/control/__init__.py
genlm/control/constant.py
genlm/control/typing.py
genlm/control/util.py
genlm/control/viz.py
genlm/control/html/smc.html
genlm/control/potential/__init__.py
genlm/control/potential/autobatch.py
genlm/control/potential/base.py
genlm/control/potential/coerce.py
genlm/control/potential/multi_proc.py
genlm/control/potential/operators.py
genlm/control/potential/product.py
genlm/control/potential/stateful.py
genlm/control/potential/streaming.py
genlm/control/potential/testing.py
genlm/control/potential/built_in/__init__.py
genlm/control/potential/built_in/canonical.py
genlm/control/potential/built_in/json.py
genlm/control/potential/built_in/llm.py
genlm/control/potential/built_in/wcfg.py
genlm/control/potential/built_in/wfsa.py
genlm/control/sampler/__init__.py
genlm/control/sampler/sequence.py
genlm/control/sampler/set.py
genlm/control/sampler/token.py
genlm_control-0.2.11.dist-info/licenses/LICENSE
genlm_control-0.2.11.dist-info/METADATA
genlm_control-0.2.11.dist-info/WHEEL
genlm_control-0.2.11.dist-info/top_level.txt
genlm_control-0.2.11.dist-info/RECORD
