Metadata-Version: 2.4
Name: genlm-control
Version: 0.2.11
Summary: Controlled generation from LMs using programmable constraints
Author: The GenLM Team
Author-email: Ben LeBrun <benlebrun1@gmail.com>
Requires-Python: >=3.11
License-File: LICENSE
Requires-Dist: genlm-grammar>=0.2.0
Requires-Dist: genlm-backend>=0.1.1
Requires-Dist: llamppl
Requires-Dist: arsenal>=3.1.3
Requires-Dist: IPython
Requires-Dist: numpy
Requires-Dist: torch
Requires-Dist: json-stream
Requires-Dist: jsonschema[format-nongpl]
Provides-Extra: test
Requires-Dist: coverage; extra == "test"
Requires-Dist: pytest; extra == "test"
Requires-Dist: pytest-benchmark; extra == "test"
Requires-Dist: pytest-asyncio; extra == "test"
Requires-Dist: pytest-timeout; extra == "test"
Requires-Dist: pytest-cov; extra == "test"
Requires-Dist: pytest-mock; extra == "test"
Requires-Dist: hypothesis==6.130.13; extra == "test"
Requires-Dist: hypothesis-jsonschema; extra == "test"
Requires-Dist: setuptools; extra == "test"
Provides-Extra: docs
Requires-Dist: mkdocs; extra == "docs"
Requires-Dist: mkdocstrings[python]; extra == "docs"
Requires-Dist: mkdocs-material; extra == "docs"
Requires-Dist: mkdocs-gen-files; extra == "docs"
Requires-Dist: mkdocs-literate-nav; extra == "docs"
Requires-Dist: mkdocs-section-index; extra == "docs"
Dynamic: license-file
